epygram/__init__.py
epygram/base.py
epygram/colormapping.py
epygram/config.py
epygram/containers.py
epygram/moves.py
epygram/profiles.py
epygram/spectra.py
epygram/util.py
epygram/_plugins/__init__.py
epygram/_plugins/util.py
epygram/_plugins/with_cartopy/AcademicGeometry.py
epygram/_plugins/with_cartopy/GaussGeometry.py
epygram/_plugins/with_cartopy/Geometry.py
epygram/_plugins/with_cartopy/H2DField.py
epygram/_plugins/with_cartopy/H2DVectorField.py
epygram/_plugins/with_cartopy/ProjectedGeometry.py
epygram/_plugins/with_cartopy/RectangularGeometry.py
epygram/_plugins/with_cartopy/__init__.py
epygram/_plugins/with_vtk/D3VectorField.py
epygram/_plugins/with_vtk/Geometry.py
epygram/_plugins/with_vtk/_D3CommonField.py
epygram/_plugins/with_vtk/__init__.py
epygram/cli/__init__.py
epygram/cli/cartoplot.py
epygram/cli/convert.py
epygram/cli/ddhlfa_plot.py
epygram/cli/delfield.py
epygram/cli/domain_maker.py
epygram/cli/fa_sp2gp.py
epygram/cli/histogram.py
epygram/cli/movefield.py
epygram/cli/plot3d.py
epygram/cli/point.py
epygram/cli/profile.py
epygram/cli/run_epyweb.py
epygram/cli/section.py
epygram/cli/spectrum.py
epygram/cli/stats.py
epygram/cli/what.py
epygram/cli/what_the_grib.py
epygram/cli/args_catalog/__init__.py
epygram/cli/args_catalog/domain_maker.py
epygram/cli/args_catalog/extraction.py
epygram/cli/args_catalog/fields.py
epygram/cli/args_catalog/files.py
epygram/cli/args_catalog/graphical.py
epygram/cli/args_catalog/misc.py
epygram/cli/args_catalog/operational.py
epygram/cli/args_catalog/output.py
epygram/cli/args_catalog/runtime.py
epygram/data/Field_Dict_LFI.csv
epygram/data/Field_Dict_netCDFMNH.csv
epygram/data/french_departments.json
epygram/data/sfxflddesc_mod.F90
epygram/data/sfxflddesc_mod.F90-49T1
epygram/data/colormaps/aspect.json
epygram/data/colormaps/gaspect.json
epygram/data/colormaps/ptype.json
epygram/data/colormaps/ptype0.json
epygram/data/colormaps/radar.json
epygram/data/colormaps/rr1h.json
epygram/data/colormaps/rr24h.json
epygram-2.0.7.dist-info/licenses/LICENSE.txt
epygram-2.0.7.dist-info/METADATA
epygram-2.0.7.dist-info/WHEEL
epygram-2.0.7.dist-info/entry_points.txt
epygram-2.0.7.dist-info/top_level.txt
epygram-2.0.7.dist-info/RECORD
