Metadata-Version: 2.4
Name: epygram
Version: 2.0.7
Summary: EPyGrAM : Enhanced Python for Graphics and Analysis of Meteorological fields
Author-email: Alexandre MARY <alexandre.mary@meteo.fr>, Sébastien Riette <sebastien.riette@meteo.fr>
Maintainer-email: Alexandre MARY <alexandre.mary@meteo.fr>, Sébastien Riette <sebastien.riette@meteo.fr>
License: 
Project-URL: documentation, https://umr-cnrm.github.io/EPyGrAM-doc
Project-URL: source, https://github.com/UMR-CNRM/EPyGrAM.git
Project-URL: download, https://github.com/UMR-CNRM/EPyGrAM/releases
Project-URL: tracker, https://github.com/UMR-CNRM/EPyGrAM/issues
Keywords: NWP,meteorology,GRIB,FA
Classifier: Development Status :: 5 - Production/Stable
Classifier: Intended Audience :: Science/Research
Classifier: Intended Audience :: Developers
Classifier: Programming Language :: Python
Classifier: Programming Language :: Python :: 3.10
Classifier: Programming Language :: Python :: 3.11
Classifier: Programming Language :: Python :: 3.12
Classifier: Operating System :: Unix
Requires-Python: >=3.10
License-File: LICENSE.txt
Requires-Dist: bronx
Requires-Dist: eccodes==2.38.1
Requires-Dist: ectrans4py==1.6.0
Requires-Dist: falfilfa4py==1.0.7
Requires-Dist: footprints
Requires-Dist: netCDF4
Requires-Dist: numpy
Requires-Dist: pyproj
Requires-Dist: pytest
Requires-Dist: pyyaml
Requires-Dist: taylorism
Provides-Extra: docs
Requires-Dist: sphinx; extra == "docs"
Requires-Dist: jupyter; extra == "docs"
Requires-Dist: nbsphinx; extra == "docs"
Provides-Extra: graphics
Requires-Dist: cartopy==0.23.0; extra == "graphics"
Requires-Dist: contourpy; extra == "graphics"
Requires-Dist: matplotlib; extra == "graphics"
Requires-Dist: vtk; extra == "graphics"
Provides-Extra: features
Requires-Dist: pyresample; extra == "features"
Requires-Dist: scipy; extra == "features"
Requires-Dist: taylorism; extra == "features"
Requires-Dist: vgrid; extra == "features"
Requires-Dist: web.py; extra == "features"
Provides-Extra: extra-formats
Requires-Dist: h5py; extra == "extra-formats"
Requires-Dist: pillow>=5.4.1; extra == "extra-formats"
Provides-Extra: all
Requires-Dist: cartopy==0.23.0; extra == "all"
Requires-Dist: contourpy; extra == "all"
Requires-Dist: h5py; extra == "all"
Requires-Dist: jupyter; extra == "all"
Requires-Dist: matplotlib; extra == "all"
Requires-Dist: nbsphinx; extra == "all"
Requires-Dist: pillow>=5.4.1; extra == "all"
Requires-Dist: pyresample; extra == "all"
Requires-Dist: scipy; extra == "all"
Requires-Dist: sphinx; extra == "all"
Requires-Dist: vgrid; extra == "all"
Requires-Dist: vtk; extra == "all"
Requires-Dist: web.py; extra == "all"
Dynamic: license-file
